{
  "text": "A Reappraisal.\u201d Explorations in \nEconomic History 22 (October): 402-16. \n \nMcFerrin, James B. 1939. Caldwell and Company. Chapel Hill: University of North Carolina Press. \n \nMeltzer, Allan H. \u201cMonetary and Other Explanations for the Start of the Great Depression.\u201d Journal of \nMonetary Economics 2 (1976): 455-72. \n \nRedenius, Scott A. \u201cHubs and Spokes: Network Effects and the Formation of Regional Banking \nCenters.\u201d Manuscript: Bryn Mawr College, February 2003. \n \nRichardson, Gary. \u201cThe Records of the Federal Reserve Board of Governors in the National Archives of \nthe United States.\u201d Financial History Review (forthcoming June 2006). \n \n----- \u201cBank Distress During the Great Contraction, 1929 to 1933, New Data From the Archives of \nthe Board of Governors.\u201d UC Irvine Mimeo, 2005. \n \nRichardson, Gary and William Troost.",
  "metadata": {
    "title": "correspondent_clearing_banking_panics",
    "source": "data\\documents\\great_depression\\processed\\correspondent_clearing_banking_panics.txt",
    "topic": "great_depression",
    "chunk_index": 101,
    "total_chunks": 105
  }
}