{
  "text": "57 percent of the \npopular vote and almost 89 \npercent of the electoral vote.Chapter 15, Section 4\n\nThe Election of 1932 \u2014Assessment\nWhat was one way President Hoover wanted to battle the Depression?\n(A) Federal relief programs\n(B) U.S. expansion into foreign markets\n(C) Stock market investment\n(D) Voluntary aid\nRoosevelt won public support from which groups? \n(A) Urban workers and coal miners\n(B) Big business executives\n(C) Supporters of international trade\n(D) Journalists and newspaper publishers\nWant to link to the Pathways Internet activity for this chapter? Click here!Chapter 15, Section 4",
  "metadata": {
    "title": "crash_and_depression",
    "source": "data\\documents\\great_depression\\processed\\crash_and_depression.txt",
    "topic": "great_depression",
    "chunk_index": 22,
    "total_chunks": 24
  }
}