{
  "text": "lands 37.4 % Sweden 10.3 % Denmark 16.5 % Poland 46.6 % Argentina 17.0 % Brazil 7.0 % Japan 8.5 % \n\nMoney and Output in the United States\n4.04.55.05.56.06.57.07.5\n1900\n1905\n1910\n19151920\n1925\n19301935\n1940YearsReal GDP in billions of 1982 $ \n(logarithms)\n1.52.02.53.03.54.04.55.05.5\nMoney supply in billions of $ \n(logarithms)Real GDP\nMoney Supply\n \n \n\nBibliography \n \nThe Great Depression in the United States \nMILTON FRIEDMAN and A NNA JACOBSON SCHWARTZ , A Monetary History of the United \nStates, 1867\u20131960 (1963, reissued 1993), chapter 7, \u201cThe Great Contraction,\u201d is the single most \nimportant study of the Great Depression in the United States, detailing ways in which banking panics and monetary contraction contributed to the economic downturn. \nScholarly studies that analyze the role of particular factors in the American Depression \ninclude: B\nEN S.",
  "metadata": {
    "title": "great_depression_romer",
    "source": "data\\documents\\great_depression\\processed\\great_depression_romer.txt",
    "topic": "great_depression",
    "chunk_index": 35,
    "total_chunks": 49
  }
}