{
  "text": "% based on the item. Europe counteracted creating a lack of trade, only worsening the depression. \n\nIn 1931 there was a Debt Moratorium where a suspension of payments for international debts was put \ninto place. The results were disas trous. \n1. The international economy suffered major loan defaults \n2. Many large dep ositors withdrew their money from banks, making it even w orse. \nHoover\u2019s Domestic Programs were Too Little, Too Late! \nThe Federal Farm Board was created in 1929 to hold wh eat and cotton in storage locations. How ever, \nthe farmers kept growing crops and overproduction increased. \nThe Reconstruction Finance Corporation (RFC) was a federally -funded , government -owned corporation \ncreated in 1932 with the goal to stabilize railroads, banks, life -insurance companies . This would create a \n\u201ctrickle -down\u201d effect on the eco nomy. However, the Democra ts were against this policy as they \nbelieved that it only catered to the rich.",
  "metadata": {
    "title": "great_depression_overview",
    "source": "data\\documents\\great_depression\\processed\\great_depression_overview.txt",
    "topic": "great_depression",
    "chunk_index": 5,
    "total_chunks": 11
  }
}