{
  "text": "of industry renders trade associations\nmore essential to sound development of our economic system\". (Hoover din-\nner speech presented at the convention of the American Trade Association\nExecutives, source: htp://www.presidency.ucsb.edu/ws/?pid=22633)\nIn his Memoirs (1952), Hoover stated:\n...the great area of indirect economic wrong and unethical practices that\nspring up under the pressures of competition...the great \feld of economic\nwaster through destructive competition, through strikes, , through failure of\nour di\u000berent industries to synchronize...I then described the possibilities of\nusing the multitude of associational activities ...to bring these ideas to reality,\nwe enlisted the di\u000berent trade associations in creation of codes of business\npractice and ethics that eliminate abuses.\" (Hoover [13])\nThere is considerable evidence that the trade associations facilitated the\ncollusion that characterized large industry in the 1920s.",
  "metadata": {
    "title": "what_started_great_depression",
    "source": "data\\documents\\great_depression\\processed\\what_started_great_depression.txt",
    "topic": "great_depression",
    "chunk_index": 21,
    "total_chunks": 114
  }
}