{
  "text": "ritish indexes gives evidence that these results are peculiar to the United\nStates.\", pp 77-78.\n12\n\nAccording to Hoover, high real wages were necessary to keep demand,\nand in turn output, high:\n\" not so many years ago, the employer considered it was in his interest to\nuse the opportunities of unemployment and immigration to lower wages... the\nlowest wages and longest hours were then conceived as the means to obtain\nhighest pro\fts. But we are a long way on the road to new conceptions. The\nvery essence of great production is high wages...because it depends upon\na widening range of consumption only to be obtained from the purchasing\npower of high real wages....\" (p. 108, Hoover [13]).\nHoover was central in advancing unionization. He promoted and signed\nlandmark unionization legislation, including the Davis-Bacon Act in 1931 and\nthe Norris-Laguardia Act in 1932, both of which raised wages and facilitated\nunionization.",
  "metadata": {
    "title": "what_started_great_depression",
    "source": "data\\documents\\great_depression\\processed\\what_started_great_depression.txt",
    "topic": "great_depression",
    "chunk_index": 25,
    "total_chunks": 114
  }
}