{
  "text": "dustry not to cut\nwages, and for long time large-scale industry adhered to pledge\", (O'Brien\n[18]). This view was echoed by Commerce Secretary Andrew Mellon, who\nnoted \"there has been a concerted and determined e\u000bort on the part of\nboth government and business...to prevent any reduction in wages.\" Time\nMagazine noted \"The United Press International interviewed business leaders\nwho attended the 1929 White House conferences, discovered an agreement\namong them that Industry, by & large, had lived up to its wage pledge.\nPierre Samuel Du Pont (I. E. du Pont de Nemours & Co.), Walter Sherman\nGi\u000bord (American Telephone & Telegraph). Jesse Isidor Straus (R. H. Macy\n& Co.) declared their companies had not reduced their wage scales since\n19",
  "metadata": {
    "title": "what_started_great_depression",
    "source": "data\\documents\\great_depression\\processed\\what_started_great_depression.txt",
    "topic": "great_depression",
    "chunk_index": 38,
    "total_chunks": 114
  }
}